vkeasybot/__init__.py
vkeasybot/callback.py
vkeasybot/longpull.py
vkeasybot/vkeasybot.py
vkeasybot-0.0.1.dist-info/LICENSE
vkeasybot-0.0.1.dist-info/METADATA
vkeasybot-0.0.1.dist-info/WHEEL
vkeasybot-0.0.1.dist-info/top_level.txt
vkeasybot-0.0.1.dist-info/RECORD
