Metadata-Version: 2.1
Name: vkeasybot
Version: 0.0.1
Summary: vkeasybot - модуль для работы с api Вконтакте
Home-page: https://github.com/Ilya001/vkeasybot
Author: ilya001
Author-email: ilja.sonin2018@yandex.ru
License: Copyright (c) 2019 The Python Packaging Authority, see LICENSE file
Platform: UNKNOWN
Requires-Dist: requests
